<?xml version="1.0" encoding="UTF-8"?>
<!DOCTYPE article PUBLIC "-//OASIS//DTD DocBook XML V4.5//EN" "../docbook-xml-4.5/docbookx.dtd">
<table>
<title>Gráfico</title>
<tgroup cols='13' align='center' colsep='1' rowsep='1'>

<tbody><row><entry>Gráfico</entry><entry>Orientação</entry><entry>Tipo de Gráfico</entry><entry>Descrição</entry><entry>Domain Label</entry><entry>Tipo de Entidade</entry><entry>Exibir Legenda</entry><entry>Time Series</entry><entry>Nome</entry><entry>Range Label</entry><entry>Time Scope</entry><entry>Unidade de Tempo</entry><entry>Altura da Janela</entry></row>
<row><entry>50003</entry><entry>V</entry><entry>BS</entry><entry> </entry><entry> </entry><entry>D</entry><entry>true</entry><entry>false</entry><entry>My Open Requests</entry><entry> </entry><entry>0</entry><entry> </entry><entry>300</entry></row>
<row><entry>50001</entry><entry>H</entry><entry>P3</entry><entry> </entry><entry>Opportunity</entry><entry>D</entry><entry>true</entry><entry>false</entry><entry>My Opportunities by Campaign</entry><entry>Campaign</entry><entry>0</entry><entry> </entry><entry>300</entry></row>
<row><entry>50000</entry><entry>V</entry><entry>BS</entry><entry> </entry><entry>Sales Stage</entry><entry>D</entry><entry>true</entry><entry>false</entry><entry>My Sales Pipeline</entry><entry>Value</entry><entry>0</entry><entry> </entry><entry>300</entry></row>
<row><entry>1500013</entry><entry>V</entry><entry>RC</entry><entry> </entry><entry> </entry><entry>BRERP0001</entry><entry>true</entry><entry>false</entry><entry>Estoque Disponivel por Categoria</entry><entry> </entry><entry>0</entry><entry> </entry><entry>0</entry></row>
<row><entry>1500042</entry><entry>V</entry><entry>RC</entry><entry> </entry><entry> </entry><entry>U</entry><entry>true</entry><entry>false</entry><entry>Clientes por Estado</entry><entry> </entry><entry>0</entry><entry> </entry><entry>300</entry></row>
<row><entry>1500047</entry><entry>V</entry><entry>WC</entry><entry> </entry><entry>Domain</entry><entry>U</entry><entry>false</entry><entry>false</entry><entry>Maiores Pedidos Hora x Dia</entry><entry>Range</entry><entry>0</entry><entry> </entry><entry>300</entry></row>
<row><entry>1500046</entry><entry>V</entry><entry>LC</entry><entry> </entry><entry> </entry><entry>U</entry><entry>false</entry><entry>true</entry><entry>Analise de Curvatura de Fluxo </entry><entry> </entry><entry>90</entry><entry>D</entry><entry>300</entry></row>
<row><entry>50002</entry><entry>V</entry><entry>LC</entry><entry> </entry><entry>Mês</entry><entry>D</entry><entry>false</entry><entry>true</entry><entry>Vendas Anuais</entry><entry>Valor</entry><entry>12</entry><entry>M</entry><entry>300</entry></row>
<row><entry>1500040</entry><entry>V</entry><entry>B3</entry><entry> </entry><entry> </entry><entry>U</entry><entry>false</entry><entry>false</entry><entry>Ranking de Vendedores</entry><entry> </entry><entry>0</entry><entry> </entry><entry>300</entry></row>
<row><entry>1500043</entry><entry>V</entry><entry>AS</entry><entry> </entry><entry> </entry><entry>U</entry><entry>false</entry><entry>true</entry><entry>Vendas Por Categoria 30 dias</entry><entry> </entry><entry>30</entry><entry>D</entry><entry>300</entry></row>
<row><entry>1500044</entry><entry>V</entry><entry>LC</entry><entry> </entry><entry> </entry><entry>U</entry><entry>false</entry><entry>true</entry><entry>Fluxo de Caixa 30 Dias</entry><entry> </entry><entry>30</entry><entry>D</entry><entry>300</entry></row>
<row><entry>1500045</entry><entry>V</entry><entry>WC</entry><entry> </entry><entry> </entry><entry>U</entry><entry>false</entry><entry>false</entry><entry>Vendas por Estado x Cidade</entry><entry> </entry><entry>0</entry><entry> </entry><entry>300</entry></row>
<row><entry>1500039</entry><entry>V</entry><entry>B3</entry><entry> </entry><entry> </entry><entry>U</entry><entry>true</entry><entry>false</entry><entry>Top 5 por Categoria de Produto</entry><entry> </entry><entry>0</entry><entry> </entry><entry>300</entry></row></tbody>
</tgroup>
</table>